Metadata-Version: 1.1
Name: uptask
Version: 0.2.0
Summary: Task Runner(Local and SSH) made in Python.
Home-page: https://github.com/allanfreitas/uptask
Author: Allan Freitas
Author-email: allanfreitasci@gmail.com
License: UNKNOWN
Keywords: tasks development runner
Platform: UNKNOWN
Classifier: Development Status :: 3 - Alpha
Classifier: Intended Audience :: Developers
Classifier: Topic :: Software Development
Classifier: License :: OSI Approved :: MIT License
Classifier: Programming Language :: Python :: 3
